{
  "permalink": "/blog/2021/12/31/using-js-keystores",
  "source": "@site/blog/2021-12-31-using-js-keystores.md",
  "title": "using-js-keystores",
  "description": "",
  "date": "2021-12-31T00:00:00.000Z",
  "formattedDate": "December 31, 2021",
  "tags": [],
  "readingTime": 0,
  "truncated": false,
  "authors": [],
  "prevItem": {
    "title": "hellocelo",
    "permalink": "/blog/2022/01/01/hellocelo"
  },
  "nextItem": {
    "title": "addtokentocelowallet",
    "permalink": "/blog/2021/12/06/addtokentocelowallet"
  }
}